mirascope/__init__.py
mirascope/_stubs.py
mirascope/_utils.py
mirascope/api/__init__.py
mirascope/api/client.py
mirascope/api/settings.py
mirascope/api/_generated/README.md
mirascope/api/_generated/__init__.py
mirascope/api/_generated/client.py
mirascope/api/_generated/environment.py
mirascope/api/_generated/reference.md
mirascope/api/_generated/annotations/__init__.py
mirascope/api/_generated/annotations/client.py
mirascope/api/_generated/annotations/raw_client.py
mirascope/api/_generated/annotations/types/__init__.py
mirascope/api/_generated/annotations/types/annotations_create_request_label.py
mirascope/api/_generated/annotations/types/annotations_create_response.py
mirascope/api/_generated/annotations/types/annotations_create_response_label.py
mirascope/api/_generated/annotations/types/annotations_get_response.py
mirascope/api/_generated/annotations/types/annotations_get_response_label.py
mirascope/api/_generated/annotations/types/annotations_list_request_label.py
mirascope/api/_generated/annotations/types/annotations_list_response.py
mirascope/api/_generated/annotations/types/annotations_list_response_annotations_item.py
mirascope/api/_generated/annotations/types/annotations_list_response_annotations_item_label.py
mirascope/api/_generated/annotations/types/annotations_update_request_label.py
mirascope/api/_generated/annotations/types/annotations_update_response.py
mirascope/api/_generated/annotations/types/annotations_update_response_label.py
mirascope/api/_generated/api_keys/__init__.py
mirascope/api/_generated/api_keys/client.py
mirascope/api/_generated/api_keys/raw_client.py
mirascope/api/_generated/api_keys/types/__init__.py
mirascope/api/_generated/api_keys/types/api_keys_create_response.py
mirascope/api/_generated/api_keys/types/api_keys_get_response.py
mirascope/api/_generated/api_keys/types/api_keys_list_all_for_org_response_item.py
mirascope/api/_generated/api_keys/types/api_keys_list_response_item.py
mirascope/api/_generated/core/__init__.py
mirascope-2.1.0.dist-info/METADATA
mirascope-2.1.0.dist-info/WHEEL
mirascope-2.1.0.dist-info/licenses/LICENSE
mirascope-2.1.0.dist-info/RECORD
