Metadata-Version: 2.4
Name: mirascope
Version: 2.1.0
Summary: Every frontier LLM. One unified interface.
Project-URL: Homepage, https://mirascope.com
Project-URL: Documentation, https://mirascope.com/docs/mirascope/v2
Project-URL: Repository, https://github.com/Mirascope/mirascope/tree/v2
Project-URL: Issues, https://github.com/Mirascope/mirascope/issues
Project-URL: Changelog, https://github.com/Mirascope/mirascope/releases
Author-email: William Bakst <william@mirascope.com>, Dandelion Mané <dandelion@mirascope.com>
Maintainer-email: William Bakst <william@mirascope.com>, Dandelion Mané <dandelion@mirascope.com>
License: MIT License
License-File: LICENSE
Keywords: agents,anthropic,artificial intelligence,context engineering,developer tools,gemini,llm,llm tools,openai,prompt engineering
Classifier: Development Status :: 5 - Production/Stable
Classifier: Intended Audience :: Developers
Classifier: License :: OSI Approved :: MIT License
Classifier: Programming Language :: Python :: 3
Classifier: Programming Language :: Python :: 3.10
Classifier: Programming Language :: Python :: 3.11
Classifier: Programming Language :: Python :: 3.12
Classifier: Programming Language :: Python :: 3.13
Classifier: Programming Language :: Python :: 3.14
Classifier: Topic :: File Formats :: JSON
Classifier: Topic :: File Formats :: JSON :: JSON Schema
Classifier: Topic :: Scientific/Engineering :: Artificial Intelligence
Classifier: Topic :: Software Development :: Libraries
Requires-Python: >=3.10
Requires-Dist: docstring-parser>=0.17.0
Requires-Dist: httpx>=0.27.0
Requires-Dist: jiter>=0.7.0
Requires-Dist: pydantic>=2.0.0
Requires-Dist: typing-extensions>=4.10.0
Provides-Extra: all
Requires-Dist: anthropic<1.0,>=0.76.0; extra == 'all'
Requires-Dist: google-genai<2,>=1.58.0; extra == 'all'
Requires-Dist: libcst>=1.8.6; extra == 'all'
Requires-Dist: mcp<2,>=1.25.0; extra == 'all'
Requires-Dist: mlx-lm<1,>=0.28.4; extra == 'all'
Requires-Dist: openai<3,>=2.15.0; extra == 'all'
Requires-Dist: opentelemetry-api<2,>=1.38.0; extra == 'all'
Requires-Dist: opentelemetry-exporter-otlp<2,>=1.38.0; extra == 'all'
Requires-Dist: opentelemetry-instrumentation-anthropic<1,>=0.50.0; extra == 'all'
Requires-Dist: opentelemetry-instrumentation-google-genai<1,>=0.3b0; extra == 'all'
Requires-Dist: opentelemetry-instrumentation-openai-v2<3,>=2.0b0; extra == 'all'
Requires-Dist: opentelemetry-instrumentation<1,>=0.59b0; extra == 'all'
Requires-Dist: opentelemetry-propagator-b3<2,>=1.38.0; extra == 'all'
Requires-Dist: opentelemetry-propagator-b3>=1.38.0; extra == 'all'
Requires-Dist: opentelemetry-propagator-jaeger>=1.38.0; extra == 'all'
Requires-Dist: opentelemetry-sdk<2,>=1.38.0; extra == 'all'
Requires-Dist: orjson>=3.11.4; extra == 'all'
Requires-Dist: packaging>=25.0; extra == 'all'
Requires-Dist: pillow<11,>=10.4.0; extra == 'all'
Requires-Dist: proto-plus>=1.24.0; extra == 'all'
Requires-Dist: pydantic-settings>=2.12.0; extra == 'all'
Provides-Extra: anthropic
Requires-Dist: anthropic<1.0,>=0.76.0; extra == 'anthropic'
Provides-Extra: api
Requires-Dist: pydantic-settings>=2.12.0; extra == 'api'
Provides-Extra: google
Requires-Dist: google-genai<2,>=1.58.0; extra == 'google'
Requires-Dist: pillow<11,>=10.4.0; extra == 'google'
Requires-Dist: proto-plus>=1.24.0; extra == 'google'
Provides-Extra: mcp
Requires-Dist: mcp<2,>=1.25.0; extra == 'mcp'
Provides-Extra: mlx
Requires-Dist: mlx-lm<1,>=0.28.4; extra == 'mlx'
Provides-Extra: openai
Requires-Dist: openai<3,>=2.15.0; extra == 'openai'
Provides-Extra: ops
Requires-Dist: libcst>=1.8.6; extra == 'ops'
Requires-Dist: opentelemetry-api<2,>=1.38.0; extra == 'ops'
Requires-Dist: opentelemetry-exporter-otlp<2,>=1.38.0; extra == 'ops'
Requires-Dist: opentelemetry-instrumentation-anthropic<1,>=0.50.0; extra == 'ops'
Requires-Dist: opentelemetry-instrumentation-google-genai<1,>=0.3b0; extra == 'ops'
Requires-Dist: opentelemetry-instrumentation-openai-v2<3,>=2.0b0; extra == 'ops'
Requires-Dist: opentelemetry-instrumentation<1,>=0.59b0; extra == 'ops'
Requires-Dist: opentelemetry-propagator-b3<2,>=1.38.0; extra == 'ops'
Requires-Dist: opentelemetry-propagator-b3>=1.38.0; extra == 'ops'
Requires-Dist: opentelemetry-propagator-jaeger>=1.38.0; extra == 'ops'
Requires-Dist: opentelemetry-sdk<2,>=1.38.0; extra == 'ops'
Requires-Dist: orjson>=3.11.4; extra == 'ops'
Requires-Dist: packaging>=25.0; extra == 'ops'
